dmjone/StudentManagementSystem.py
dmjone/__init__.py
dmjone/hello.py
dmjone/lab4.py
dmjone/aarushi/__init__.py
dmjone/aarushi/aarushi_todolist.py
dmjone/anurag/__init__.py
dmjone/gaurav/__init__.py
dmjone/kaustuv/__init__.py
dmjone/kaustuv/kaustuv_common.py
dmjone/kaustuv/kaustuv_project.py
dmjone/lakshika/__init__.py
dmjone/lakshika/calculator.py
dmjone/lakshika/lakshika_functions.py
dmjone/lakshika/typecasting.py
dmjone/team5/ashutosh.py
dmjone/team5/test.py
dmjone-0.2.dist-info/LICENSE
dmjone-0.2.dist-info/METADATA
dmjone-0.2.dist-info/WHEEL
dmjone-0.2.dist-info/top_level.txt
dmjone-0.2.dist-info/RECORD
