Metadata-Version: 2.1
Name: dmjone
Version: 0.2
Summary: Public Welfare initiatives by dmj.one - Educational Initiative
Author-email: Divya Mohan <contact@dmj.one>
Maintainer-email: Aarushi Sharma <aarushi@dmj.one>, Kaustuv Sharma <kaustuv@dmj.one>, Lakshika Tanwar <lakshika@dmj.one>
License: GNU GENERAL PUBLIC LICENSE
Project-URL: homepage, https://dmj.one
Project-URL: repository, https://github.com/dmjone/dmjone_pypi
Project-URL: bug_tracker, https://github.com/dmjone/dmjone_pypi/issues
Keywords: education,public welfare initiative,learning resources,shoolini university,dmjone
Classifier: Development Status :: 4 - Beta
Classifier: Environment :: Web Environment
Classifier: Intended Audience :: Education
Classifier: Intended Audience :: Developers
Classifier: License :: OSI Approved :: GNU General Public License v3 (GPLv3)
Classifier: Natural Language :: English
Classifier: Operating System :: OS Independent
Classifier: Programming Language :: Python :: 3
Classifier: Programming Language :: Python :: 3.7
Classifier: Programming Language :: Python :: 3.8
Classifier: Programming Language :: Python :: 3.9
Classifier: Topic :: Education
Classifier: Topic :: Software Development :: Libraries :: Python Modules
Requires-Python: >=3.7
License-File: LICENSE
Requires-Dist: mysql-connector-python >=8.0.23
Requires-Dist: Faker >=8.1.1
Requires-Dist: Flask >=1.1.2
Requires-Dist: requests >=2.25.1
Provides-Extra: testing
Requires-Dist: pytest >=6.2.4 ; extra == 'testing'
Requires-Dist: coverage >=5.5 ; extra == 'testing'
